abs_geolocation_core/__init__.py
abs_geolocation_core/location_service.py
abs_geolocation_core-0.1.1.dist-info/METADATA
abs_geolocation_core-0.1.1.dist-info/WHEEL
abs_geolocation_core-0.1.1.dist-info/RECORD
