Metadata-Version: 2.3
Name: abs-geolocation-core
Version: 0.1.1
Summary: Shared service for the azure maps location service
License: MIT
Author: AutoBridgeSystems
Author-email: info@autobridgesystems.com
Requires-Python: >=3.11,<4.0
Classifier: License :: OSI Approved :: MIT License
Classifier: Programming Language :: Python :: 3
Classifier: Programming Language :: Python :: 3.11
Classifier: Programming Language :: Python :: 3.12
Classifier: Programming Language :: Python :: 3.13
Provides-Extra: dev
Provides-Extra: test
Requires-Dist: azure-core
Requires-Dist: azure-identity (>=1.24.0,<2.0.0)
Requires-Dist: azure-maps-route (>=1.0.0b3,<2.0.0)
Requires-Dist: azure-maps-search (>=2.0.0b2,<3.0.0)
Requires-Dist: azure-mgmt-maps (>=2.1.0,<3.0.0)
Requires-Dist: black (>=23.0.0) ; extra == "dev"
Requires-Dist: coverage[toml] (>=7.0.0) ; extra == "test"
Requires-Dist: dependency-injector (>=4.48.1,<5.0.0)
Requires-Dist: fastapi (>=0.100.0)
Requires-Dist: flake8 (>=6.0.0) ; extra == "dev"
Requires-Dist: httpx (>=0.28.1,<0.29.0)
Requires-Dist: isort (>=5.12.0) ; extra == "dev"
Requires-Dist: mypy (>=1.0.0) ; extra == "dev"
Requires-Dist: pre-commit (>=3.0.0) ; extra == "dev"
Requires-Dist: pydantic (>=2.0.0)
Requires-Dist: pytest (>=7.0.0) ; extra == "test"
Requires-Dist: pytest-asyncio (>=0.21.0) ; extra == "test"
Requires-Dist: pytest-cov (>=4.0.0) ; extra == "test"
Requires-Dist: pytest-mock (>=3.10.0) ; extra == "test"
